git_fleet_manager/__init__.py
git_fleet_manager/cli.py
git_fleet_manager/git_utils.py
git_fleet_manager-1.0.5.dist-info/METADATA
git_fleet_manager-1.0.5.dist-info/WHEEL
git_fleet_manager-1.0.5.dist-info/entry_points.txt
git_fleet_manager-1.0.5.dist-info/licenses/LICENSE
git_fleet_manager-1.0.5.dist-info/RECORD
