Metadata-Version: 2.4
Name: git_fleet_manager
Version: 1.0.5
Summary: A command line tool for managing several git repositories at once
Project-URL: Homepage, https://github.com/diefenbach/git-fleet-manager
Author-email: Kai Diefenbach <kai.diefenbach@iqpp.de>
License-File: LICENSE
Classifier: Environment :: Console
Classifier: License :: OSI Approved :: MIT License
Classifier: Operating System :: OS Independent
Classifier: Programming Language :: Python :: 3
Requires-Python: >=3.8
